{"artefacts":[{"description":"configuration folder","extractedfiles":[{"actions":[{"mandatory":true,"path":"startpath","overwrite":true,"adictional_path":"","type":"copy"}],"language":"portuguese","file":"ecdlivro_a.xml","description":"layout a ecd","localization":["bra"]},{"actions":[{"mandatory":true,"path":"startpath","overwrite":true,"adictional_path":"","type":"copy"}],"language":"portuguese","file":"ecdlivro_b.xml","description":"layout b ecd","localization":["bra"]},{"actions":[{"mandatory":true,"path":"startpath","overwrite":true,"adictional_path":"","type":"copy"}],"language":"portuguese","file":"ecdlivro_g.xml","description":"layout g ecd","localization":["bra"]},{"actions":[{"mandatory":true,"path":"startpath","overwrite":true,"adictional_path":"","type":"copy"}],"language":"portuguese","file":"ecdlivro_r.xml","description":"layout r ecd","localization":["bra"]},{"actions":[{"mandatory":true,"path":"startpath","overwrite":true,"adictional_path":"","type":"copy"}],"language":"portuguese","file":"ecdlivro_z.xml","description":"layout z ecd","localization":["bra"]},{"actions":[{"mandatory":true,"path":"startpath","overwrite":true,"adictional_path":"/system/","type":"copy"}],"language":"portuguese","file":"tc_cfg0001.json","description":"arquivo de configuracao 0001"},{"actions":[{"mandatory":true,"path":"startpath","overwrite":true,"adictional_path":"/system/","type":"copy"}],"language":"portuguese","file":"tc_cfg0002.json","description":"arquivo de configuracao 0002"},{"actions":[{"mandatory":true,"path":"startpath","overwrite":true,"adictional_path":"/system/","type":"copy"}],"language":"portuguese","file":"tc_cfg0003.json","description":"arquivo de configuracao 0003"},{"actions":[{"mandatory":true,"path":"startpath","overwrite":true,"adictional_path":"/system/","type":"copy"}],"language":"portuguese","file":"tc_cfg0004.json","description":"arquivo de configuracao 0004"},{"actions":[{"mandatory":true,"path":"startpath","overwrite":true,"adictional_path":"/system/","type":"copy"}],"language":"portuguese","file":"tc_cfg0005.json","description":"arquivo de configuracao 0005"},{"actions":[{"mandatory":true,"path":"startpath","overwrite":true,"adictional_path":"/system/","type":"copy"}],"language":"portuguese","file":"tc_cfg0006.json","description":"arquivo de configuracao 0006"},{"actions":[{"mandatory":true,"path":"startpath","overwrite":true,"adictional_path":"/system/","type":"copy"}],"language":"portuguese","file":"tc_cfg0007.json","description":"arquivo de configuracao 0007"},{"actions":[{"mandatory":true,"path":"startpath","overwrite":true,"adictional_path":"/system/","type":"copy"}],"language":"portuguese","file":"tc_cfg0008.json","description":"arquivo de configuracao 0008"},{"actions":[{"mandatory":true,"path":"startpath","overwrite":true,"adictional_path":"/system/","type":"copy"}],"language":"portuguese","file":"tc_cfg0009.json","description":"arquivo de configuracao 0009"},{"actions":[{"mandatory":true,"path":"startpath","overwrite":true,"adictional_path":"/system/","type":"copy"}],"language":"portuguese","file":"tc_cfg0010.json","description":"arquivo de configuracao 0010"},{"actions":[{"mandatory":true,"path":"startpath","overwrite":true,"adictional_path":"/system/","type":"copy"}],"language":"portuguese","file":"tc_cfg0011.json","description":"arquivo de configuracao 0011"},{"actions":[{"mandatory":true,"path":"startpath","overwrite":true,"adictional_path":"/system/","type":"copy"}],"language":"portuguese","file":"tc_cfg0012.json","description":"arquivo de configuracao 0012"},{"actions":[{"mandatory":true,"path":"startpath","overwrite":true,"adictional_path":"/system/","type":"copy"}],"language":"portuguese","file":"tc_cfg0013.json","description":"arquivo de configuracao 0013"},{"actions":[{"mandatory":true,"path":"startpath","overwrite":true,"adictional_path":"/system/","type":"copy"}],"language":"portuguese","file":"tc_cfg0014.json","description":"arquivo de configuracao 0014"},{"actions":[{"mandatory":true,"path":"startpath","overwrite":true,"adictional_path":"/system/","type":"copy"}],"language":"portuguese","file":"tc_cfg0015.json","description":"arquivo de configuracao 0015"},{"actions":[{"mandatory":true,"path":"startpath","overwrite":true,"adictional_path":"/system/","type":"copy"}],"language":"portuguese","file":"tc_cfg0016.json","description":"arquivo de configuracao 0016"},{"actions":[{"mandatory":true,"path":"startpath","overwrite":true,"adictional_path":"/system/","type":"copy"}],"language":"portuguese","file":"tc_cfg0017.json","description":"arquivo de configuracao 00117"},{"actions":[{"mandatory":true,"path":"startpath","overwrite":true,"adictional_path":"/system/","type":"copy"}],"language":"portuguese","file":"tc_cfg0018.json","description":"arquivo de configuracao 0018"},{"actions":[{"mandatory":true,"path":"startpath","overwrite":true,"adictional_path":"/system/","type":"copy"}],"language":"portuguese","file":"tc_cfg0019.json","description":"arquivo de configuracao 0019"},{"actions":[{"mandatory":true,"path":"startpath","overwrite":true,"adictional_path":"/system/","type":"copy"}],"language":"portuguese","file":"tc_cfg0020.json","description":"arquivo de configuracao 0020"},{"actions":[{"mandatory":true,"path":"startpath","overwrite":true,"adictional_path":"/system/","type":"copy"}],"language":"portuguese","file":"tc_cfg0021.json","description":"arquivo de configuracao 0021"},{"actions":[{"path":"rootpath","overwrite":true,"adictional_path":"","type":"copy"}],"language":"portuguese","file":"ecf_regl100a.cve","description":"files ecf_regl100a","localization":["bra"]},{"actions":[{"path":"rootpath","overwrite":true,"adictional_path":"","type":"copy"}],"language":"portuguese","file":"ecf_regl100b.cve","description":"files ecf_regl100b","localization":["bra"]},{"actions":[{"path":"rootpath","overwrite":true,"adictional_path":"","type":"copy"}],"language":"portuguese","file":"ecf_regl100c.cve","description":"files ecf_regl100c","localization":["bra"]},{"actions":[{"path":"rootpath","overwrite":true,"adictional_path":"","type":"copy"}],"language":"portuguese","file":"ecf_regl210.cve","description":"files ecf_regl210","localization":["bra"]},{"actions":[{"path":"rootpath","overwrite":true,"adictional_path":"","type":"copy"}],"language":"portuguese","file":"ecf_regl300a.cve","description":"files ecf_regl300a","localization":["bra"]},{"actions":[{"path":"rootpath","overwrite":true,"adictional_path":"","type":"copy"}],"language":"portuguese","file":"ecf_regl300b.cve","description":"files ecf_regl300b","localization":["bra"]},{"actions":[{"path":"rootpath","overwrite":true,"adictional_path":"","type":"copy"}],"language":"portuguese","file":"ecf_regl300c.cve","description":"files ecf_regl300c","localization":["bra"]},{"actions":[{"path":"rootpath","overwrite":true,"adictional_path":"","type":"copy"}],"language":"portuguese","file":"ecf_regp100.cve","description":"files ecf_regp100","localization":["bra"]},{"actions":[{"path":"rootpath","overwrite":true,"adictional_path":"","type":"copy"}],"language":"portuguese","file":"ecf_regp130.cve","description":"files ecf_regp130","localization":["bra"]},{"actions":[{"path":"rootpath","overwrite":true,"adictional_path":"","type":"copy"}],"language":"portuguese","file":"ecf_regp150.cve","description":"files ecf_regp150","localization":["bra"]},{"actions":[{"path":"rootpath","overwrite":true,"adictional_path":"","type":"copy"}],"language":"portuguese","file":"ecf_regp200.cve","description":"files ecf_regp200","localization":["bra"]},{"actions":[{"path":"rootpath","overwrite":true,"adictional_path":"","type":"copy"}],"language":"portuguese","file":"ecf_regp230.cve","description":"files ecf_regp230","localization":["bra"]},{"actions":[{"path":"rootpath","overwrite":true,"adictional_path":"","type":"copy"}],"language":"portuguese","file":"ecf_regp300.cve","description":"files ecf_regp300","localization":["bra"]},{"actions":[{"path":"rootpath","overwrite":true,"adictional_path":"","type":"copy"}],"language":"portuguese","file":"ecf_regp400.cve","description":"files ecf_regp400","localization":["bra"]},{"actions":[{"path":"rootpath","overwrite":true,"adictional_path":"","type":"copy"}],"language":"portuguese","file":"ecf_regp500.cve","description":"files ecf_regp500","localization":["bra"]},{"actions":[{"path":"rootpath","overwrite":true,"adictional_path":"","type":"copy"}],"language":"portuguese","file":"ecf_regt120.cve","description":"files ecf_regt120","localization":["bra"]},{"actions":[{"path":"rootpath","overwrite":true,"adictional_path":"","type":"copy"}],"language":"portuguese","file":"ecf_regt150.cve","description":"files ecf_regt150","localization":["bra"]},{"actions":[{"path":"rootpath","overwrite":true,"adictional_path":"","type":"copy"}],"language":"portuguese","file":"ecf_regt170.cve","description":"files ecf_regt170","localization":["bra"]},{"actions":[{"path":"rootpath","overwrite":true,"adictional_path":"","type":"copy"}],"language":"portuguese","file":"ecf_regt181.cve","description":"files ecf_regt181","localization":["bra"]},{"actions":[{"path":"rootpath","overwrite":false,"adictional_path":"","type":"copy"}],"language":"portuguese","file":"ecf_regu100a.cve","description":"files ecf_regu100a","localization":["bra"]},{"actions":[{"path":"rootpath","overwrite":true,"adictional_path":"","type":"copy"}],"language":"portuguese","file":"ecf_regu100b.cve","description":"files ecf_regu100b","localization":["bra"]},{"actions":[{"path":"rootpath","overwrite":false,"adictional_path":"","type":"copy"}],"language":"portuguese","file":"ecf_regu100c.cve","description":"files ecf_regu100c","localization":["bra"]},{"actions":[{"path":"rootpath","overwrite":true,"adictional_path":"","type":"copy"}],"language":"portuguese","file":"ecf_regu100d.cve","description":"files ecf_regu100d","localization":["bra"]},{"actions":[{"path":"rootpath","overwrite":true,"adictional_path":"","type":"copy"}],"language":"portuguese","file":"ecf_regu100e.cve","description":"files ecf_regu100e","localization":["bra"]},{"actions":[{"path":"rootpath","overwrite":true,"adictional_path":"","type":"copy"}],"language":"portuguese","file":"ecf_regu150a.cve","description":"files ecf_regu150a","localization":["bra"]},{"actions":[{"path":"rootpath","overwrite":true,"adictional_path":"","type":"copy"}],"language":"portuguese","file":"ecf_regu150b.cve","description":"files ecf_regu150b","localization":["bra"]},{"actions":[{"path":"rootpath","overwrite":true,"adictional_path":"","type":"copy"}],"language":"portuguese","file":"ecf_regu150c.cve","description":"files ecf_regu150c","localization":["bra"]},{"actions":[{"path":"rootpath","overwrite":true,"adictional_path":"","type":"copy"}],"language":"portuguese","file":"ecf_regu150d.cve","description":"files ecf_regu150d","localization":["bra"]},{"actions":[{"path":"rootpath","overwrite":true,"adictional_path":"","type":"copy"}],"language":"portuguese","file":"ecf_regu150e.cve","description":"files ecf_regu150e","localization":["bra"]},{"actions":[{"path":"rootpath","overwrite":true,"adictional_path":"","type":"copy"}],"language":"portuguese","file":"ecf_regu180.cve","description":"files ecf_regu180","localization":["bra"]},{"actions":[{"path":"rootpath","overwrite":true,"adictional_path":"","type":"copy"}],"language":"portuguese","file":"ecf_regu182.cve","description":"files ecf_regu182","localization":["bra"]},{"actions":[{"path":"rootpath","overwrite":true,"adictional_path":"","type":"copy"}],"language":"portuguese","file":"ecf_regv100.cve","description":"files ecf_regv100","localization":["bra"]},{"actions":[{"path":"rootpath","overwrite":true,"adictional_path":"","type":"copy"}],"language":"portuguese","file":"ecf_regx350.cve","description":"files ecf_regx350","localization":["bra"]},{"actions":[{"path":"rootpath","overwrite":true,"adictional_path":"","type":"copy"}],"language":"portuguese","file":"ecf_regx390.cve","description":"files ecf_regx390","localization":["bra"]},{"actions":[{"path":"rootpath","overwrite":true,"adictional_path":"","type":"copy"}],"language":"portuguese","file":"ecf_regx400.cve","description":"files ecf_regx400","localization":["bra"]},{"actions":[{"path":"rootpath","overwrite":true,"adictional_path":"","type":"copy"}],"language":"portuguese","file":"ecf_regx460.cve","description":"files ecf_regx460","localization":["bra"]},{"actions":[{"path":"rootpath","overwrite":true,"adictional_path":"","type":"copy"}],"language":"portuguese","file":"ecf_regx470.cve","description":"files ecf_regx470","localization":["bra"]},{"actions":[{"path":"rootpath","overwrite":true,"adictional_path":"","type":"copy"}],"language":"portuguese","file":"ecf_regx480.cve","description":"files ecf_regx480","localization":["bra"]},{"actions":[{"path":"rootpath","overwrite":true,"adictional_path":"","type":"copy"}],"language":"portuguese","file":"ecf_regx490.cve","description":"files ecf_regx490","localization":["bra"]},{"actions":[{"path":"rootpath","overwrite":true,"adictional_path":"","type":"copy"}],"language":"portuguese","file":"ecf_regx500.cve","description":"files ecf_regx500","localization":["bra"]},{"actions":[{"path":"rootpath","overwrite":true,"adictional_path":"","type":"copy"}],"language":"portuguese","file":"ecf_regx510.cve","description":"files ecf_regx510","localization":["bra"]},{"actions":[{"path":"rootpath","overwrite":true,"adictional_path":"","type":"copy"}],"language":"portuguese","file":"ecf_regy671.cve","description":"files ecf_regy671","localization":["bra"]},{"actions":[{"path":"rootpath","overwrite":true,"adictional_path":"","type":"copy"}],"language":"portuguese","file":"ecf_regy672.cve","description":"files ecf_regy672","localization":["bra"]},{"actions":[{"path":"rootpath","overwrite":true,"adictional_path":"","type":"copy"}],"language":"portuguese","file":"ecf_regy681.cve","description":"files ecf_regy681","localization":["bra"]},{"actions":[{"mandatory":true,"path":"startpath","overwrite":true,"adictional_path":"","type":"copy"}],"language":"portuguese","file":"ecd.ch","description":"files ecd.ch","localization":["bra"]},{"actions":[{"mandatory":true,"path":"startpath","overwrite":true,"adictional_path":"","type":"copy"}],"language":"portuguese","file":"ecf.ch","description":"files ecf.ch","localization":["bra"]},{"actions":[{"mandatory":true,"path":"startpath","overwrite":true,"adictional_path":"","type":"copy"}],"language":"portuguese","file":"banner.png","description":"banner.png","localization":["bra"]}],"localization":["bra"],"language":"portuguese","actions":[{"mandatory":true,"path":"rootpath","overwrite":true,"adictional_path":"","type":"extract"}],"file":"config.zip"},{"localization":["bra","arg","col","mex","chi","per"],"actions":[{"path":"rootpath","overwrite":true,"adictional_path":"\\systemload","type":"copy"},{"name":"upddistr","type":"function"}],"description":"folder whith database update files","directory":"sdf"},{"actions":[{"type":"info"}],"file":"chamados.txt","description":"list of issues"},{"actions":[{"type":"info"}],"file":"chamados.html","description":"list of issues"},{"db_type":"top","description":"update patch","localization":["all"],"actions":[{"mandatory":true,"type":"apply_patch"}],"language":"multi","file":"expedicao_continua_12_1_33_ctb_tttm120_hp.ptm","patch_type":"harpia"},{"actions":[{"type":"info"}],"file":"expedicao_continua_12.1.33_ctb_contents.txt","description":"list of sources"}],"metainfo":{"build":"20230512","id":"695172","name":"expedicao_continua_12.1.33_ctb","type":"continuous-delivery","version":"12.1.033"}}